Metadata-Version: 1.0
Name: itemzer
Version: 1.1.0
Summary: Module for getting informations for League of Legend champions
Home-page: https://github.com/p0lux/Itemzer
Author: p0
Author-email: kylian.p@protonmail.ch
License: UNKNOWN
Platform: UNKNOWN
